snowflake_sqlalchemy_json/__init__.py
snowflake_sqlalchemy_json-1.1.2.dist-info/LICENSE
snowflake_sqlalchemy_json-1.1.2.dist-info/METADATA
snowflake_sqlalchemy_json-1.1.2.dist-info/WHEEL
snowflake_sqlalchemy_json-1.1.2.dist-info/top_level.txt
snowflake_sqlalchemy_json-1.1.2.dist-info/zip-safe
snowflake_sqlalchemy_json-1.1.2.dist-info/RECORD
